embedme/__init__.py
embedme/embedme.py
embedme-0.1.6.dist-info/LICENSE
embedme-0.1.6.dist-info/METADATA
embedme-0.1.6.dist-info/WHEEL
embedme-0.1.6.dist-info/RECORD
