Metadata-Version: 2.1
Name: embedme
Version: 0.1.6
Summary: Easily create and search text embeddings using OpenAI's API using json for local storage. Just add dicts of info and search! Built for rapid prototyping.
Home-page: https://github.com/morganpartee/embedme
License: GPL-3.0-or-later
Keywords: nlp,embeddings,search,openai,gpt3,AI,machine learning
Author: John Partee
Requires-Python: >=3.8,<3.13
Classifier: License :: OSI Approved :: GNU General Public License v3 or later (GPLv3+)
Classifier: Programming Language :: Python :: 3
Classifier: Programming Language :: Python :: 3.8
Classifier: Programming Language :: Python :: 3.9
Classifier: Programming Language :: Python :: 3.10
Classifier: Programming Language :: Python :: 3.11
Classifier: Programming Language :: Python :: 3.12
Requires-Dist: numpy (>=1.24.1,<2.0.0)
Requires-Dist: openai (>=1.30.2,<2.0.0)
Project-URL: Repository, https://github.com/morganpartee/embedme
